odoo/addons/maintenance_equipment_custom_info/README.rst
odoo/addons/maintenance_equipment_custom_info/__init__.py
odoo/addons/maintenance_equipment_custom_info/__manifest__.py
odoo/addons/maintenance_equipment_custom_info/i18n/it.po
odoo/addons/maintenance_equipment_custom_info/i18n/maintenance_equipment_custom_info.pot
odoo/addons/maintenance_equipment_custom_info/models/__init__.py
odoo/addons/maintenance_equipment_custom_info/models/maintenance_equipment.py
odoo/addons/maintenance_equipment_custom_info/readme/CONTRIBUTORS.rst
odoo/addons/maintenance_equipment_custom_info/readme/DESCRIPTION.rst
odoo/addons/maintenance_equipment_custom_info/static/description/icon.png
odoo/addons/maintenance_equipment_custom_info/static/description/index.html
odoo/addons/maintenance_equipment_custom_info/views/maintenance_equipment.xml
odoo14_addon_maintenance_equipment_custom_info-14.0.1.0.1.dist-info/METADATA
odoo14_addon_maintenance_equipment_custom_info-14.0.1.0.1.dist-info/WHEEL
odoo14_addon_maintenance_equipment_custom_info-14.0.1.0.1.dist-info/top_level.txt
odoo14_addon_maintenance_equipment_custom_info-14.0.1.0.1.dist-info/RECORD
